LoopAi/LoopAi.py
LoopAi/__init__.py
LoopAi-1.0.3.dist-info/METADATA
LoopAi-1.0.3.dist-info/WHEEL
LoopAi-1.0.3.dist-info/top_level.txt
LoopAi-1.0.3.dist-info/RECORD
